{
  "playlistCollection": [
    {
      "id": "02",
      "title": "Beethoven Concertos",
      "songs": [
        {
          "id": "07",
          "title": "Piano Concerto No. 0",
          "artist": "Beethoven"
        },
        {
          "id": "09",
          "title": "Piano Concerto No. 6",
          "artist": "Beethoven"
        }
      ]
    },
    {
      "id": "a317f541-115d-488c-a451-ed780fa80e62",
      "title": "gg",
      "date": "2026-04-24T10:10:30.804Z",
      "songs": []
    }
  ]
}